Sitea/Sitea.py
Sitea/__init__.py
Sitea/run.py
Sitea-0.1.0.dist-info/METADATA
Sitea-0.1.0.dist-info/WHEEL
Sitea-0.1.0.dist-info/top_level.txt
Sitea-0.1.0.dist-info/RECORD
