Metadata-Version: 2.1
Name: Sitea
Version: 0.1.0
Summary: A simple website-making library based on streamlit for AI, uses Neuraforge gemini library
Author: Aaroh Charne
Author-email: aaroh.charne@gmail.com
Classifier: Programming Language :: Python :: 3
Classifier: License :: OSI Approved :: MIT License
Classifier: Operating System :: OS Independent
Classifier: Development Status :: 3 - Alpha
Classifier: Intended Audience :: Developers
Classifier: Natural Language :: English
Classifier: Topic :: Software Development :: Libraries :: Python Modules
Requires-Python: >=3.6
Requires-Dist: streamlit
Requires-Dist: NeuraForge
